flaskmotion/__init__.py
flaskmotion/routes.py
flaskmotion/static/css/flaskmotion.css
flaskmotion/static/js/flaskmotion.js
flaskmotion/templates/base.html
flaskmotion-0.1.8.dist-info/METADATA
flaskmotion-0.1.8.dist-info/WHEEL
flaskmotion-0.1.8.dist-info/top_level.txt
flaskmotion-0.1.8.dist-info/RECORD
