Metadata-Version: 2.1
Name: flaskmotion
Version: 0.1.8
Summary: A Flask package for smooth page transitions using AJAX and CSS fade effects.
Home-page: https://github.com/beukzdev/flaskmotion
Author: Daniël Beukes
Author-email: your_email@example.com
Classifier: Programming Language :: Python :: 3
Classifier: License :: OSI Approved :: MIT License
Classifier: Operating System :: OS Independent
Requires-Python: >=3.6
Requires-Dist: Flask >=1.1
